dynamiq/__init__.py
dynamiq/cache/__init__.py
dynamiq/cache/backends/__init__.py
dynamiq/cache/backends/base.py
dynamiq/cache/backends/redis.py
dynamiq/cache/codecs.py
dynamiq/cache/config.py
dynamiq/cache/managers/__init__.py
dynamiq/cache/managers/base.py
dynamiq/cache/managers/workflow.py
dynamiq/cache/utils.py
dynamiq/callbacks/__init__.py
dynamiq/callbacks/base.py
dynamiq/callbacks/streaming.py
dynamiq/callbacks/tracing.py
dynamiq/cli/__init__.py
dynamiq/cli/client.py
dynamiq/cli/commands/__init__.py
dynamiq/cli/commands/config.py
dynamiq/cli/commands/context.py
dynamiq/cli/commands/org.py
dynamiq/cli/commands/project.py
dynamiq/cli/commands/resource_profiles.py
dynamiq/cli/commands/service.py
dynamiq/cli/commands/utils.py
dynamiq/cli/config.py
dynamiq/clients/__init__.py
dynamiq/clients/base.py
dynamiq/clients/dynamiq.py
dynamiq/components/__init__.py
dynamiq/components/converters/__init__.py
dynamiq/components/converters/base.py
dynamiq/components/converters/docx.py
dynamiq/components/converters/html.py
dynamiq/components/converters/pptx.py
dynamiq/components/converters/pypdf.py
dynamiq/components/converters/text.py
dynamiq/components/converters/unstructured.py
dynamiq/components/converters/utils.py
dynamiq/components/embedders/__init__.py
dynamiq/components/embedders/base.py
dynamiq/components/embedders/bedrock.py
dynamiq/components/embedders/cohere.py
dynamiq/components/embedders/gemini.py
dynamiq/components/embedders/huggingface.py
dynamiq/components/embedders/mistral.py
dynamiq/components/embedders/openai.py
dynamiq/components/embedders/vertexai.py
dynamiq/components/embedders/watsonx.py
dynamiq/components/retrievers/__init__.py
dynamiq/components/retrievers/chroma.py
dynamiq/components/retrievers/elasticsearch.py
dynamiq/components/retrievers/milvus.py
dynamiq/components/retrievers/opensearch.py
dynamiq/components/retrievers/pgvector.py
dynamiq/components/retrievers/pinecone.py
dynamiq/components/retrievers/qdrant.py
dynamiq-0.36.1.dist-info/LICENSE
dynamiq-0.36.1.dist-info/METADATA
dynamiq-0.36.1.dist-info/WHEEL
dynamiq-0.36.1.dist-info/entry_points.txt
dynamiq-0.36.1.dist-info/RECORD
