Metadata-Version: 2.1
Name: dynamiq
Version: 0.36.1
Summary: Dynamiq is an orchestration framework for agentic AI and LLM applications
Home-page: https://www.getdynamiq.ai
License: Apache-2.0
Keywords: ai,gpt,agents,rag,llm,generative-ai,llmops
Author: Dynamiq Team
Author-email: hello@getdynamiq.ai
Requires-Python: >=3.10,<3.14
Classifier: License :: OSI Approved :: Apache Software License
Classifier: Programming Language :: Python :: 3
Classifier: Programming Language :: Python :: 3.10
Classifier: Programming Language :: Python :: 3.11
Classifier: Programming Language :: Python :: 3.12
Classifier: Topic :: Scientific/Engineering :: Artificial Intelligence
Classifier: Topic :: Software Development :: Libraries :: Application Frameworks
Classifier: Topic :: Software Development :: Libraries :: Python Modules
Requires-Dist: RestrictedPython (>=8.0,<8.1)
Requires-Dist: black (>=24.8.0,<24.9.0)
Requires-Dist: boto3 (>=1.34.34,<1.35.0)
Requires-Dist: charset-normalizer (>=3.4.2,<4.0.0)
Requires-Dist: chromadb-client (>=0.5.5.dev0,<0.6.0)
Requires-Dist: databricks-sql-connector (>=4.0.3,<4.1.0)
Requires-Dist: datamodel-code-generator (==0.30.0)
Requires-Dist: e2b (==2.8.0)
Requires-Dist: e2b-code-interpreter (>=2.0.0,<2.1.0)
Requires-Dist: elasticsearch (>=8.12.0,<8.13.0)
Requires-Dist: filetype (>=1.2.0,<1.3.0)
Requires-Dist: google-cloud-aiplatform (>=1.93.0,<1.94.0)
Requires-Dist: jinja2 (>=3.1.6,<3.2.0)
Requires-Dist: jsonpath-ng (>=1.6.1,<1.7.0)
Requires-Dist: jsonpickle (>=3.0.3,<3.1.0)
Requires-Dist: litellm (==1.78.0)
Requires-Dist: lxml (>=5.3.1,<6.0.0)
Requires-Dist: matplotlib (>=3.10.7,<4.0.0)
Requires-Dist: mcp (==1.10.0)
Requires-Dist: more-itertools (>=10.3.0,<10.4.0)
Requires-Dist: mysql-connector-python (>=9.1.0,<9.2.0)
Requires-Dist: neo4j (>=6.0.3,<7.0.0)
Requires-Dist: numpy (>=1.26.0,<1.27.0)
Requires-Dist: omegaconf (>=2.3.0,<2.4.0)
Requires-Dist: openai (>=1.83.0)
Requires-Dist: openpyxl (>=3.1.5,<4.0.0)
Requires-Dist: opensearch-py (>=3.0.0,<4.0.0)
Requires-Dist: orjson (==3.10.18)
Requires-Dist: pdf2image (>=1.17.0,<1.18.0)
Requires-Dist: pdfplumber (>=0.11.8,<0.12.0)
Requires-Dist: pgvector (>=0.3.6,<0.4.0)
Requires-Dist: pinecone-client (>=3.2.2,<3.3.0)
Requires-Dist: psycopg[binary] (>=3.2.3,<3.3.0)
Requires-Dist: pydantic (>=2.11.7,<2.12.0)
Requires-Dist: pymilvus (>=2.5.6,<2.6.0)
Requires-Dist: pypdf (>=6.3.0,<6.4.0)
Requires-Dist: pypdf2 (>=3.0.1,<4.0.0)
Requires-Dist: python-docx (>=1.1.2,<2.0.0)
Requires-Dist: python-pptx (==1.0.2)
Requires-Dist: pyyaml (==6.0.1)
Requires-Dist: qdrant-client (>=1.11.3,<1.12.0)
Requires-Dist: rapidfuzz (>=3.11.0,<3.12.0)
Requires-Dist: redis (>=5.0.0,<5.1.0)
Requires-Dist: regex (>=2025.9.18,<2026.0.0)
Requires-Dist: requests (>=2.32.5,<3.0.0)
Requires-Dist: requests-aws4auth (>=1.3.1,<2.0.0)
Requires-Dist: rouge-score (>=0.1.2,<0.2.0)
Requires-Dist: sacrebleu (>=2.5.1,<2.6.0)
Requires-Dist: seaborn (>=0.13.2,<0.14.0)
Requires-Dist: snowflake-connector-python (>=3.13.2,<3.14.0)
Requires-Dist: tenacity (==9.1.2)
Requires-Dist: tiktoken (==0.12.0)
Requires-Dist: unstructured-client (>=0.42.3,<0.43.0)
Requires-Dist: weaviate-client (>=4.7.1,<4.8.0)
Project-URL: Documentation, https://dynamiq-ai.github.io/dynamiq
Project-URL: Repository, https://github.com/dynamiq-ai/dynamiq
